azure_recommendations_11/__init__.py
azure_recommendations_11/recommendation/__init__.py
azure_recommendations_11/recommendation/advisor_recommendations.py
azure_recommendations_11/recommendation/network_recommendations.py
azure_recommendations_11/recommendation/utils.py
azure_recommendations_11/recommendation/vm_recommendations.py
azure_recommendations_11-0.2.0.dist-info/LICENCE
azure_recommendations_11-0.2.0.dist-info/METADATA
azure_recommendations_11-0.2.0.dist-info/WHEEL
azure_recommendations_11-0.2.0.dist-info/top_level.txt
azure_recommendations_11-0.2.0.dist-info/RECORD
